Metadata-Version: 1.1
Name: basic-algorithms
Version: 0.1.2
Summary: Basic algorithms
Home-page: https://github.com/rajasekhar-varikuti/algorithms
Author: Rajasekhar Varikuti
Author-email: rajasekhar.cse537@gmail.com
License: MIT
Download-URL: https://github.com/rajasekhar-varikuti/algorithms/archive/algorithms_v_01.tar.gz
Keywords: Algorithms,sorting,sorting algorithms
Platform: UNKNOWN
Classifier: Development Status :: 3 - Alpha
Classifier: Intended Audience :: Developers
Classifier: Topic :: Software Development :: Build Tools
Classifier: License :: OSI Approved :: MIT License
Classifier: Programming Language :: Python :: 3
Classifier: Programming Language :: Python :: 3.4
Classifier: Programming Language :: Python :: 3.5
Classifier: Programming Language :: Python :: 3.6
Classifier: Programming Language :: Python :: 3.7
